README.md
setup.py
qqdm/__init__.py
qqdm/core.py
qqdm.egg-info/PKG-INFO
qqdm.egg-info/SOURCES.txt
qqdm.egg-info/dependency_links.txt
qqdm.egg-info/requires.txt
qqdm.egg-info/top_level.txt