Metadata-Version: 2.1
Name: qqdm
Version: 0.0.1
Summary: A multi-line logging toolkit.
Home-page: https://github.com/kimythanly/qqdm
Author: KimythAnly
Author-email: kimythanly@gmail.com
License: UNKNOWN
Platform: UNKNOWN
Classifier: Programming Language :: Python :: 3
Classifier: License :: OSI Approved :: MIT License
Classifier: Operating System :: OS Independent
Requires-Python: >=3.6
